setup.py
fushare/__init__.py
fushare/basis.py
fushare/calendar.json
fushare/cons.py
fushare/cot.py
fushare/dailyBar.py
fushare/receipt.py
fushare/requests_fun.py
fushare/rollYield.py
fushare/sendEmail.py
fushare/symbolVar.py
fushare.egg-info/PKG-INFO
fushare.egg-info/SOURCES.txt
fushare.egg-info/dependency_links.txt
fushare.egg-info/requires.txt
fushare.egg-info/top_level.txt