Metadata-Version: 1.0
Name: fushare
Version: 1.2.10
Summary: A utility for fundamentals data of China commodity futures
Home-page: https://github.com/LowinLi/fushare
Author: LowinLi
Author-email: li783170560@126.cn
License: UNKNOWN
Keywords: Fundmentals Commodity Future Data
Platform: UNKNOWN
